pyflunearyou/__init__.py
pyflunearyou/cdc.py
pyflunearyou/client.py
pyflunearyou/errors.py
pyflunearyou/helpers/__init__.py
pyflunearyou/helpers/geo.py
pyflunearyou/helpers/report.py
pyflunearyou/py.typed
pyflunearyou/user.py
pyflunearyou-2021.10.0.dist-info/LICENSE
pyflunearyou-2021.10.0.dist-info/WHEEL
pyflunearyou-2021.10.0.dist-info/METADATA
pyflunearyou-2021.10.0.dist-info/RECORD
