Metadata-Version: 2.1
Name: pyflunearyou
Version: 2021.10.0
Summary: A clean, well-tested Python3 API for Flu Near You
Home-page: https://github.com/bachya/pyflunearyou
License: MIT
Author: Aaron Bach
Author-email: bachya1208@gmail.com
Requires-Python: >=3.6.1,<4.0.0
Classifier: License :: OSI Approved :: MIT License
Classifier: Programming Language :: Python
Classifier: Programming Language :: Python :: 3
Classifier: Programming Language :: Python :: 3.10
Classifier: Programming Language :: Python :: 3.6
Classifier: Programming Language :: Python :: 3.7
Classifier: Programming Language :: Python :: 3.8
Classifier: Programming Language :: Python :: 3.9
Classifier: Programming Language :: Python :: Implementation :: CPython
Classifier: Programming Language :: Python :: Implementation :: PyPy
Requires-Dist: aiocache (>=0.11.1,<0.12.0)
Requires-Dist: aiohttp (>=3.7.4,<4.0.0)
Requires-Dist: msgpack (>=0.6.2,<1.1.0)
Requires-Dist: ujson (>=1.35,<5.0)
Project-URL: Repository, https://github.com/bachya/pyflunearyou
